pulseel/__init__.py
pulseel/extractors/__init__.py
pulseel/extractors/mongo.py
pulseel/extractors/rdbms/__init__.py
pulseel/extractors/rdbms/mssql.py
pulseel/loaders/__init__.py
pulseel/loaders/az.py
pulseel/loaders/filesystem.py
pulseel/pipelines/__init__.py
pulseel/pipelines/mongo_to_az.py
pulseel/pipelines/mssql_to_az.py
pulseel/utils/__init__.py
pulseel/utils/datetimes.py
pulseel/utils/helpers.py
pulseel/utils/models.py
pulseel/utils/typing.py
pulse_extractor_loader-0.1.1.dist-info/METADATA
pulse_extractor_loader-0.1.1.dist-info/WHEEL
pulse_extractor_loader-0.1.1.dist-info/entry_points.txt
pulse_extractor_loader-0.1.1.dist-info/top_level.txt
pulse_extractor_loader-0.1.1.dist-info/RECORD
