Metadata-Version: 2.4
Name: pulse-extractor-loader
Version: 0.1.1
Summary: Projeto focado em criar scripts de extracão de dados de diversos tipos de sistemas externos e efetuar
Requires-Python: >=3.12
Requires-Dist: adlfs>=2024.12.0
Requires-Dist: polars>=1.21.0
Requires-Dist: psycopg2-binary>=2.9.10
Requires-Dist: pymongo>=3
Requires-Dist: pymongoarrow>=1.6.4
Requires-Dist: pymssql>=2.3.2
Requires-Dist: python-dotenv>=1.0.1
Requires-Dist: sqlalchemy>=2.0.37
Requires-Dist: sqlparse>=0.5.3
Requires-Dist: typer>=0.15.1
